dsw_sdk/__init__.py
dsw_sdk/sdk.py
dsw_sdk/common/__init__.py
dsw_sdk/common/attributes.py
dsw_sdk/common/snapshot.py
dsw_sdk/common/types.py
dsw_sdk/common/utils.py
dsw_sdk/config/__init__.py
dsw_sdk/config/config.py
dsw_sdk/high_level_api/__init__.py
dsw_sdk/high_level_api/app_config_api.py
dsw_sdk/high_level_api/common_api.py
dsw_sdk/high_level_api/document_api.py
dsw_sdk/high_level_api/package_api.py
dsw_sdk/high_level_api/questionnaire_api.py
dsw_sdk/high_level_api/template_api.py
dsw_sdk/high_level_api/user_api.py
dsw_sdk/high_level_api/dto/__init__.py
dsw_sdk/high_level_api/dto/app_config.py
dsw_sdk/high_level_api/dto/common.py
dsw_sdk/high_level_api/dto/knowledge_model.py
dsw_sdk/high_level_api/dto/questionnaire.py
dsw_sdk/high_level_api/dto/template.py
dsw_sdk/high_level_api/dto/user.py
dsw_sdk/high_level_api/models/__init__.py
dsw_sdk/high_level_api/models/app_config.py
dsw_sdk/high_level_api/models/document.py
dsw_sdk/high_level_api/models/model.py
dsw_sdk/high_level_api/models/questionnaire.py
dsw_sdk/high_level_api/models/user.py
dsw_sdk/high_level_api/models/templates/__init__.py
dsw_sdk/high_level_api/models/templates/template.py
dsw_sdk/high_level_api/models/templates/template_asset.py
dsw_sdk/high_level_api/models/templates/template_file.py
dsw_sdk/http_client/__init__.py
dsw_sdk/http_client/interface.py
dsw_sdk/http_client/requests_impl/__init__.py
dsw_sdk/http_client/requests_impl/auth.py
dsw_sdk/http_client/requests_impl/http_client.py
dsw_sdk/low_level_api/__init__.py
dsw_sdk/low_level_api/api.py
dsw_sdk-3.8.0.dist-info/LICENSE
dsw_sdk-3.8.0.dist-info/METADATA
dsw_sdk-3.8.0.dist-info/WHEEL
dsw_sdk-3.8.0.dist-info/top_level.txt
dsw_sdk-3.8.0.dist-info/RECORD
