Metadata-Version: 2.1
Name: dsw-sdk
Version: 3.8.0
Summary: Software development kit for the Data Stewardship Wizard.
Home-page: https://github.com/ds-wizard/dsw-sdk
Author: Jakub Drahoš
Author-email: jakubdrahosJD@gmail.com
License: UNKNOWN
Project-URL: Bug Tracker, https://github.com/ds-wizard/dsw-sdk/issues
Platform: UNKNOWN
Classifier: Development Status :: 5 - Production/Stable
Classifier: License :: OSI Approved :: Apache Software License
Classifier: Operating System :: OS Independent
Classifier: Programming Language :: Python :: 3
Classifier: Programming Language :: Python :: 3.7
Classifier: Programming Language :: Python :: 3.8
Classifier: Programming Language :: Python :: 3.9
Classifier: Topic :: Software Development :: Libraries
Classifier: Topic :: Software Development :: Libraries :: Python Modules
Classifier: Topic :: Utilities
Requires-Python: >=3.7
License-File: LICENSE
Requires-Dist: pyjwt
Requires-Dist: pyyaml
Requires-Dist: requests
